{
  "a_comp_cor_00": {
    "CumulativeVarianceExplained": 0.052886208,
    "Mask": "combined",
    "Method": "aCompCor",
    "Retained": true,
    "SingularValue": 124.2221307172,
    "VarianceExplained": 0.052886208
  },
  "a_comp_cor_01": {
    "CumulativeVarianceExplained": 0.093140324,
    "Mask": "combined",
    "Method": "aCompCor",
    "Retained": true,
    "SingularValue": 108.3759473987,
    "VarianceExplained": 0.040254116
  },
  "a_comp_cor_02": {
    "CumulativeVarianceExplained": 0.1234850429,
    "Mask": "combined",
    "Method": "aCompCor",
    "Retained": true,
    "SingularValue": 94.0956007896,
    "VarianceExplained": 0.0303447189
  },
  "a_comp_cor_03": {
    "CumulativeVarianceExplained": 0.1496269636,
    "Mask": "combined",
    "Method": "aCompCor",
    "Retained": true,
    "SingularValue": 87.3366454031,
    "VarianceExplained": 0.0261419207
  },
  "a_comp_cor_04": {
    "CumulativeVarianceExplained": 0.1700358452,
    "Mask": "combined",
    "Method": "aCompCor",
    "Retained": true,
    "SingularValue": 77.1680210527,
    "VarianceExplained": 0.0204088816
  },
  "a_comp_cor_05": {
    "CumulativeVarianceExplained": 0.1880859071,
    "Mask": "combined",
    "Method": "aCompCor",
    "Retained": true,
    "SingularValue": 72.5716683158,
    "VarianceExplained": 0.0180500618
  },
  "a_comp_cor_06": {
    "CumulativeVarianceExplained": 0.2045481609,
    "Mask": "combined",
    "Method": "aCompCor",
    "Retained": true,
    "SingularValue": 69.3062510408,
    "VarianceExplained": 0.0164622539
  },
  "a_comp_cor_07": {
    "CumulativeVarianceExplained": 0.2181989594,
    "Mask": "combined",
    "Method": "aCompCor",
    "Retained": true,
    "SingularValue": 63.1112507362,
    "VarianceExplained": 0.0136507984
  },
  "a_comp_cor_08": {
    "CumulativeVarianceExplained": 0.2304771517,
    "Mask": "combined",
    "Method": "aCompCor",
    "Retained": true,
    "SingularValue": 59.8542476135,
    "VarianceExplained": 0.0122781923
  },
  "a_comp_cor_09": {
    "CumulativeVarianceExplained": 0.241555545,
    "Mask": "combined",
    "Method": "aCompCor",
    "Retained": true,
    "SingularValue": 56.8546708984,
    "VarianceExplained": 0.0110783933
  },
  "a_comp_cor_10": {
    "CumulativeVarianceExplained": 0.2520227559,
    "Mask": "combined",
    "Method": "aCompCor",
    "Retained": true,
    "SingularValue": 55.2641184956,
    "VarianceExplained": 0.0104672109
  },
  "a_comp_cor_11": {
    "CumulativeVarianceExplained": 0.2622329577,
    "Mask": "combined",
    "Method": "aCompCor",
    "Retained": true,
    "SingularValue": 54.5814315323,
    "VarianceExplained": 0.0102102018
  },
  "a_comp_cor_12": {
    "CumulativeVarianceExplained": 0.271943959,
    "Mask": "combined",
    "Method": "aCompCor",
    "Retained": true,
    "SingularValue": 53.2304045604,
    "VarianceExplained": 0.0097110013
  },
  "a_comp_cor_13": {
    "CumulativeVarianceExplained": 0.2812185445,
    "Mask": "combined",
    "Method": "aCompCor",
    "Retained": true,
    "SingularValue": 52.0205589075,
    "VarianceExplained": 0.0092745855
  },
  "a_comp_cor_14": {
    "CumulativeVarianceExplained": 0.2900768952,
    "Mask": "combined",
    "Method": "aCompCor",
    "Retained": true,
    "SingularValue": 50.8398422503,
    "VarianceExplained": 0.0088583507
  },
  "a_comp_cor_15": {
    "CumulativeVarianceExplained": 0.2986718481,
    "Mask": "combined",
    "Method": "aCompCor",
    "Retained": true,
    "SingularValue": 50.078292429,
    "VarianceExplained": 0.008594953
  },
  "a_comp_cor_16": {
    "CumulativeVarianceExplained": 0.3071661998,
    "Mask": "combined",
    "Method": "aCompCor",
    "Retained": true,
    "SingularValue": 49.7843543464,
    "VarianceExplained": 0.0084943517
  },
  "a_comp_cor_17": {
    "CumulativeVarianceExplained": 0.3153050734,
    "Mask": "combined",
    "Method": "aCompCor",
    "Retained": true,
    "SingularValue": 48.7315149234,
    "VarianceExplained": 0.0081388736
  },
  "a_comp_cor_18": {
    "CumulativeVarianceExplained": 0.3233880727,
    "Mask": "combined",
    "Method": "aCompCor",
    "Retained": true,
    "SingularValue": 48.5639529146,
    "VarianceExplained": 0.0080829993
  },
  "a_comp_cor_19": {
    "CumulativeVarianceExplained": 0.3313152473,
    "Mask": "combined",
    "Method": "aCompCor",
    "Retained": true,
    "SingularValue": 48.0935652553,
    "VarianceExplained": 0.0079271746
  },
  "a_comp_cor_20": {
    "CumulativeVarianceExplained": 0.3391570465,
    "Mask": "combined",
    "Method": "aCompCor",
    "Retained": true,
    "SingularValue": 47.8338807095,
    "VarianceExplained": 0.0078417991
  },
  "a_comp_cor_21": {
    "CumulativeVarianceExplained": 0.3468582898,
    "Mask": "combined",
    "Method": "aCompCor",
    "Retained": true,
    "SingularValue": 47.4032570883,
    "VarianceExplained": 0.0077012433
  },
  "a_comp_cor_22": {
    "CumulativeVarianceExplained": 0.3544952692,
    "Mask": "combined",
    "Method": "aCompCor",
    "Retained": true,
    "SingularValue": 47.2050615953,
    "VarianceExplained": 0.0076369794
  },
  "a_comp_cor_23": {
    "CumulativeVarianceExplained": 0.3620214337,
    "Mask": "combined",
    "Method": "aCompCor",
    "Retained": true,
    "SingularValue": 46.8613305403,
    "VarianceExplained": 0.0075261646
  },
  "a_comp_cor_24": {
    "CumulativeVarianceExplained": 0.3694638327,
    "Mask": "combined",
    "Method": "aCompCor",
    "Retained": true,
    "SingularValue": 46.5998194745,
    "VarianceExplained": 0.007442399
  },
  "a_comp_cor_25": {
    "CumulativeVarianceExplained": 0.3768619916,
    "Mask": "combined",
    "Method": "aCompCor",
    "Retained": true,
    "SingularValue": 46.4611106037,
    "VarianceExplained": 0.0073981589
  },
  "a_comp_cor_26": {
    "CumulativeVarianceExplained": 0.3841624256,
    "Mask": "combined",
    "Method": "aCompCor",
    "Retained": true,
    "SingularValue": 46.1532298334,
    "VarianceExplained": 0.007300434
  },
  "a_comp_cor_27": {
    "CumulativeVarianceExplained": 0.3913598739,
    "Mask": "combined",
    "Method": "aCompCor",
    "Retained": true,
    "SingularValue": 45.8265367496,
    "VarianceExplained": 0.0071974483
  },
  "a_comp_cor_28": {
    "CumulativeVarianceExplained": 0.3985042277,
    "Mask": "combined",
    "Method": "aCompCor",
    "Retained": true,
    "SingularValue": 45.6571960806,
    "VarianceExplained": 0.0071443538
  },
  "a_comp_cor_29": {
    "CumulativeVarianceExplained": 0.4055846324,
    "Mask": "combined",
    "Method": "aCompCor",
    "Retained": true,
    "SingularValue": 45.4523978463,
    "VarianceExplained": 0.0070804047
  },
  "a_comp_cor_30": {
    "CumulativeVarianceExplained": 0.4125888119,
    "Mask": "combined",
    "Method": "aCompCor",
    "Retained": true,
    "SingularValue": 45.2070737785,
    "VarianceExplained": 0.0070041796
  },
  "a_comp_cor_31": {
    "CumulativeVarianceExplained": 0.4195122466,
    "Mask": "combined",
    "Method": "aCompCor",
    "Retained": true,
    "SingularValue": 44.9457423816,
    "VarianceExplained": 0.0069234346
  },
  "a_comp_cor_32": {
    "CumulativeVarianceExplained": 0.4263677513,
    "Mask": "combined",
    "Method": "aCompCor",
    "Retained": true,
    "SingularValue": 44.7247043132,
    "VarianceExplained": 0.0068555047
  },
  "a_comp_cor_33": {
    "CumulativeVarianceExplained": 0.4331701877,
    "Mask": "combined",
    "Method": "aCompCor",
    "Retained": true,
    "SingularValue": 44.5512613857,
    "VarianceExplained": 0.0068024364
  },
  "a_comp_cor_34": {
    "CumulativeVarianceExplained": 0.4398938716,
    "Mask": "combined",
    "Method": "aCompCor",
    "Retained": true,
    "SingularValue": 44.2926233149,
    "VarianceExplained": 0.0067236839
  },
  "a_comp_cor_35": {
    "CumulativeVarianceExplained": 0.4465498545,
    "Mask": "combined",
    "Method": "aCompCor",
    "Retained": true,
    "SingularValue": 44.0690674611,
    "VarianceExplained": 0.006655983
  },
  "a_comp_cor_36": {
    "CumulativeVarianceExplained": 0.4531368382,
    "Mask": "combined",
    "Method": "aCompCor",
    "Retained": true,
    "SingularValue": 43.8400512346,
    "VarianceExplained": 0.0065869837
  },
  "a_comp_cor_37": {
    "CumulativeVarianceExplained": 0.4596286235,
    "Mask": "combined",
    "Method": "aCompCor",
    "Retained": true,
    "SingularValue": 43.5220991564,
    "VarianceExplained": 0.0064917853
  },
  "a_comp_cor_38": {
    "CumulativeVarianceExplained": 0.4660664823,
    "Mask": "combined",
    "Method": "aCompCor",
    "Retained": true,
    "SingularValue": 43.3409557962,
    "VarianceExplained": 0.0064378588
  },
  "a_comp_cor_39": {
    "CumulativeVarianceExplained": 0.4724783735,
    "Mask": "combined",
    "Method": "aCompCor",
    "Retained": true,
    "SingularValue": 43.2534575579,
    "VarianceExplained": 0.0064118911
  },
  "a_comp_cor_40": {
    "CumulativeVarianceExplained": 0.4788724072,
    "Mask": "combined",
    "Method": "aCompCor",
    "Retained": true,
    "SingularValue": 43.193184411,
    "VarianceExplained": 0.0063940338
  },
  "a_comp_cor_41": {
    "CumulativeVarianceExplained": 0.4852285125,
    "Mask": "combined",
    "Method": "aCompCor",
    "Retained": true,
    "SingularValue": 43.0648856854,
    "VarianceExplained": 0.0063561052
  },
  "a_comp_cor_42": {
    "CumulativeVarianceExplained": 0.4914872827,
    "Mask": "combined",
    "Method": "aCompCor",
    "Retained": true,
    "SingularValue": 42.7338738284,
    "VarianceExplained": 0.0062587702
  },
  "a_comp_cor_43": {
    "CumulativeVarianceExplained": 0.4976900673,
    "Mask": "combined",
    "Method": "aCompCor",
    "Retained": true,
    "SingularValue": 42.5423142793,
    "VarianceExplained": 0.0062027846
  },
  "a_comp_cor_44": {
    "CumulativeVarianceExplained": 0.5037952226,
    "Mask": "combined",
    "Method": "aCompCor",
    "Retained": true,
    "SingularValue": 42.2061867061,
    "VarianceExplained": 0.0061051552
  },
  "c_comp_cor_00": {
    "CumulativeVarianceExplained": 0.1452064874,
    "Mask": "CSF",
    "Method": "aCompCor",
    "Retained": true,
    "SingularValue": 69.3486760028,
    "VarianceExplained": 0.1452064874
  },
  "c_comp_cor_01": {
    "CumulativeVarianceExplained": 0.2428226211,
    "Mask": "CSF",
    "Method": "aCompCor",
    "Retained": true,
    "SingularValue": 56.8598834751,
    "VarianceExplained": 0.0976161337
  },
  "c_comp_cor_02": {
    "CumulativeVarianceExplained": 0.3140643572,
    "Mask": "CSF",
    "Method": "aCompCor",
    "Retained": true,
    "SingularValue": 48.5749554723,
    "VarianceExplained": 0.0712417361
  },
  "c_comp_cor_03": {
    "CumulativeVarianceExplained": 0.357223894,
    "Mask": "CSF",
    "Method": "aCompCor",
    "Retained": true,
    "SingularValue": 37.807986691,
    "VarianceExplained": 0.0431595368
  },
  "c_comp_cor_04": {
    "CumulativeVarianceExplained": 0.3935326704,
    "Mask": "CSF",
    "Method": "aCompCor",
    "Retained": true,
    "SingularValue": 34.6777547557,
    "VarianceExplained": 0.0363087764
  },
  "c_comp_cor_05": {
    "CumulativeVarianceExplained": 0.4260744037,
    "Mask": "CSF",
    "Method": "aCompCor",
    "Retained": true,
    "SingularValue": 32.8295934478,
    "VarianceExplained": 0.0325417333
  },
  "c_comp_cor_06": {
    "CumulativeVarianceExplained": 0.4519341851,
    "Mask": "CSF",
    "Method": "aCompCor",
    "Retained": true,
    "SingularValue": 29.2656105216,
    "VarianceExplained": 0.0258597814
  },
  "c_comp_cor_07": {
    "CumulativeVarianceExplained": 0.4763442314,
    "Mask": "CSF",
    "Method": "aCompCor",
    "Retained": true,
    "SingularValue": 28.4334439808,
    "VarianceExplained": 0.0244100464
  },
  "c_comp_cor_08": {
    "CumulativeVarianceExplained": 0.4986075071,
    "Mask": "CSF",
    "Method": "aCompCor",
    "Retained": true,
    "SingularValue": 27.1543677582,
    "VarianceExplained": 0.0222632756
  },
  "c_comp_cor_09": {
    "CumulativeVarianceExplained": 0.5179665331,
    "Mask": "CSF",
    "Method": "aCompCor",
    "Retained": true,
    "SingularValue": 25.3213534973,
    "VarianceExplained": 0.0193590261
  },
  "dropped_0": {
    "CumulativeVarianceExplained": 0.401263349,
    "Mask": "Edge",
    "Method": "EdgeRegressor",
    "Retained": false,
    "SingularValue": 111.5084598758,
    "VarianceExplained": 0.0062317128
  },
  "dropped_1": {
    "CumulativeVarianceExplained": 0.4074107524,
    "Mask": "Edge",
    "Method": "EdgeRegressor",
    "Retained": false,
    "SingularValue": 110.7515862246,
    "VarianceExplained": 0.0061474033
  },
  "dropped_10": {
    "CumulativeVarianceExplained": 0.4589228003,
    "Mask": "Edge",
    "Method": "EdgeRegressor",
    "Retained": false,
    "SingularValue": 104.2415672574,
    "VarianceExplained": 0.0054459502
  },
  "dropped_100": {
    "CumulativeVarianceExplained": 0.8411600966,
    "Mask": "Edge",
    "Method": "EdgeRegressor",
    "Retained": false,
    "SingularValue": 84.0040628479,
    "VarianceExplained": 0.0035366524
  },
  "dropped_101": {
    "CumulativeVarianceExplained": 0.8446762437,
    "Mask": "Edge",
    "Method": "EdgeRegressor",
    "Retained": false,
    "SingularValue": 83.7601837647,
    "VarianceExplained": 0.0035161471
  },
  "dropped_102": {
    "CumulativeVarianceExplained": 0.8481762161,
    "Mask": "Edge",
    "Method": "EdgeRegressor",
    "Retained": false,
    "SingularValue": 83.5673079843,
    "VarianceExplained": 0.0034999724
  },
  "dropped_103": {
    "CumulativeVarianceExplained": 0.851673909,
    "Mask": "Edge",
    "Method": "EdgeRegressor",
    "Retained": false,
    "SingularValue": 83.5400894307,
    "VarianceExplained": 0.0034976928
  },
  "dropped_104": {
    "CumulativeVarianceExplained": 0.8551543675,
    "Mask": "Edge",
    "Method": "EdgeRegressor",
    "Retained": false,
    "SingularValue": 83.334019954,
    "VarianceExplained": 0.0034804585
  },
  "dropped_105": {
    "CumulativeVarianceExplained": 0.858613374,
    "Mask": "Edge",
    "Method": "EdgeRegressor",
    "Retained": false,
    "SingularValue": 83.0768057313,
    "VarianceExplained": 0.0034590065
  },
  "dropped_106": {
    "CumulativeVarianceExplained": 0.8620629725,
    "Mask": "Edge",
    "Method": "EdgeRegressor",
    "Retained": false,
    "SingularValue": 82.9637514191,
    "VarianceExplained": 0.0034495986
  },
  "dropped_107": {
    "CumulativeVarianceExplained": 0.8655000965,
    "Mask": "Edge",
    "Method": "EdgeRegressor",
    "Retained": false,
    "SingularValue": 82.8136070782,
    "VarianceExplained": 0.003437124
  },
  "dropped_108": {
    "CumulativeVarianceExplained": 0.8689356729,
    "Mask": "Edge",
    "Method": "EdgeRegressor",
    "Retained": false,
    "SingularValue": 82.7949601014,
    "VarianceExplained": 0.0034355763
  },
  "dropped_109": {
    "CumulativeVarianceExplained": 0.8723502232,
    "Mask": "Edge",
    "Method": "EdgeRegressor",
    "Retained": false,
    "SingularValue": 82.5412162536,
    "VarianceExplained": 0.0034145504
  },
  "dropped_11": {
    "CumulativeVarianceExplained": 0.4642983831,
    "Mask": "Edge",
    "Method": "EdgeRegressor",
    "Retained": false,
    "SingularValue": 103.565922732,
    "VarianceExplained": 0.0053755828
  },
  "dropped_110": {
    "CumulativeVarianceExplained": 0.8757585012,
    "Mask": "Edge",
    "Method": "EdgeRegressor",
    "Retained": false,
    "SingularValue": 82.4653684516,
    "VarianceExplained": 0.003408278
  },
  "dropped_111": {
    "CumulativeVarianceExplained": 0.8791521066,
    "Mask": "Edge",
    "Method": "EdgeRegressor",
    "Retained": false,
    "SingularValue": 82.2876712201,
    "VarianceExplained": 0.0033936054
  },
  "dropped_112": {
    "CumulativeVarianceExplained": 0.8825265493,
    "Mask": "Edge",
    "Method": "EdgeRegressor",
    "Retained": false,
    "SingularValue": 82.0550153133,
    "VarianceExplained": 0.0033744427
  },
  "dropped_113": {
    "CumulativeVarianceExplained": 0.8858910029,
    "Mask": "Edge",
    "Method": "EdgeRegressor",
    "Retained": false,
    "SingularValue": 81.9334750496,
    "VarianceExplained": 0.0033644536
  },
  "dropped_114": {
    "CumulativeVarianceExplained": 0.8892432316,
    "Mask": "Edge",
    "Method": "EdgeRegressor",
    "Retained": false,
    "SingularValue": 81.7844848498,
    "VarianceExplained": 0.0033522287
  },
  "dropped_115": {
    "CumulativeVarianceExplained": 0.8925712095,
    "Mask": "Edge",
    "Method": "EdgeRegressor",
    "Retained": false,
    "SingularValue": 81.4881228661,
    "VarianceExplained": 0.0033279778
  },
  "dropped_116": {
    "CumulativeVarianceExplained": 0.8958866595,
    "Mask": "Edge",
    "Method": "EdgeRegressor",
    "Retained": false,
    "SingularValue": 81.3346011588,
    "VarianceExplained": 0.00331545
  },
  "dropped_117": {
    "CumulativeVarianceExplained": 0.8991906529,
    "Mask": "Edge",
    "Method": "EdgeRegressor",
    "Retained": false,
    "SingularValue": 81.1939540268,
    "VarianceExplained": 0.0033039935
  },
  "dropped_118": {
    "CumulativeVarianceExplained": 0.9024868672,
    "Mask": "Edge",
    "Method": "EdgeRegressor",
    "Retained": false,
    "SingularValue": 81.0983124493,
    "VarianceExplained": 0.0032962142
  },
  "dropped_119": {
    "CumulativeVarianceExplained": 0.9057626968,
    "Mask": "Edge",
    "Method": "EdgeRegressor",
    "Retained": false,
    "SingularValue": 80.8471573737,
    "VarianceExplained": 0.0032758296
  },
  "dropped_12": {
    "CumulativeVarianceExplained": 0.4696104463,
    "Mask": "Edge",
    "Method": "EdgeRegressor",
    "Retained": false,
    "SingularValue": 102.9522205121,
    "VarianceExplained": 0.0053120632
  },
  "dropped_120": {
    "CumulativeVarianceExplained": 0.9090235894,
    "Mask": "Edge",
    "Method": "EdgeRegressor",
    "Retained": false,
    "SingularValue": 80.6626249,
    "VarianceExplained": 0.0032608926
  },
  "dropped_121": {
    "CumulativeVarianceExplained": 0.9122728465,
    "Mask": "Edge",
    "Method": "EdgeRegressor",
    "Retained": false,
    "SingularValue": 80.5185854868,
    "VarianceExplained": 0.0032492571
  },
  "dropped_122": {
    "CumulativeVarianceExplained": 0.9155005785,
    "Mask": "Edge",
    "Method": "EdgeRegressor",
    "Retained": false,
    "SingularValue": 80.2514399066,
    "VarianceExplained": 0.003227732
  },
  "dropped_123": {
    "CumulativeVarianceExplained": 0.9187130898,
    "Mask": "Edge",
    "Method": "EdgeRegressor",
    "Retained": false,
    "SingularValue": 80.0620008398,
    "VarianceExplained": 0.0032125114
  },
  "dropped_124": {
    "CumulativeVarianceExplained": 0.9219061516,
    "Mask": "Edge",
    "Method": "EdgeRegressor",
    "Retained": false,
    "SingularValue": 79.8192710006,
    "VarianceExplained": 0.0031930617
  },
  "dropped_125": {
    "CumulativeVarianceExplained": 0.9250944894,
    "Mask": "Edge",
    "Method": "EdgeRegressor",
    "Retained": false,
    "SingularValue": 79.7602060948,
    "VarianceExplained": 0.0031883378
  },
  "dropped_126": {
    "CumulativeVarianceExplained": 0.9282757891,
    "Mask": "Edge",
    "Method": "EdgeRegressor",
    "Retained": false,
    "SingularValue": 79.6721233989,
    "VarianceExplained": 0.0031812997
  },
  "dropped_127": {
    "CumulativeVarianceExplained": 0.931441635,
    "Mask": "Edge",
    "Method": "EdgeRegressor",
    "Retained": false,
    "SingularValue": 79.4783775194,
    "VarianceExplained": 0.003165846
  },
  "dropped_128": {
    "CumulativeVarianceExplained": 0.9345946012,
    "Mask": "Edge",
    "Method": "EdgeRegressor",
    "Retained": false,
    "SingularValue": 79.3165395761,
    "VarianceExplained": 0.0031529662
  },
  "dropped_129": {
    "CumulativeVarianceExplained": 0.9377396026,
    "Mask": "Edge",
    "Method": "EdgeRegressor",
    "Retained": false,
    "SingularValue": 79.2162934521,
    "VarianceExplained": 0.0031450013
  },
  "dropped_13": {
    "CumulativeVarianceExplained": 0.4748457173,
    "Mask": "Edge",
    "Method": "EdgeRegressor",
    "Retained": false,
    "SingularValue": 102.2053627534,
    "VarianceExplained": 0.005235271
  },
  "dropped_130": {
    "CumulativeVarianceExplained": 0.9408739636,
    "Mask": "Edge",
    "Method": "EdgeRegressor",
    "Retained": false,
    "SingularValue": 79.0821763734,
    "VarianceExplained": 0.0031343611
  },
  "dropped_131": {
    "CumulativeVarianceExplained": 0.9439882869,
    "Mask": "Edge",
    "Method": "EdgeRegressor",
    "Retained": false,
    "SingularValue": 78.8289867071,
    "VarianceExplained": 0.0031143232
  },
  "dropped_132": {
    "CumulativeVarianceExplained": 0.947084468,
    "Mask": "Edge",
    "Method": "EdgeRegressor",
    "Retained": false,
    "SingularValue": 78.5990474511,
    "VarianceExplained": 0.0030961812
  },
  "dropped_133": {
    "CumulativeVarianceExplained": 0.9501709976,
    "Mask": "Edge",
    "Method": "EdgeRegressor",
    "Retained": false,
    "SingularValue": 78.476445192,
    "VarianceExplained": 0.0030865296
  },
  "dropped_134": {
    "CumulativeVarianceExplained": 0.953230983,
    "Mask": "Edge",
    "Method": "EdgeRegressor",
    "Retained": false,
    "SingularValue": 78.1382676813,
    "VarianceExplained": 0.0030599854
  },
  "dropped_135": {
    "CumulativeVarianceExplained": 0.9562846256,
    "Mask": "Edge",
    "Method": "EdgeRegressor",
    "Retained": false,
    "SingularValue": 78.0572427354,
    "VarianceExplained": 0.0030536426
  },
  "dropped_136": {
    "CumulativeVarianceExplained": 0.9593232689,
    "Mask": "Edge",
    "Method": "EdgeRegressor",
    "Retained": false,
    "SingularValue": 77.865300114,
    "VarianceExplained": 0.0030386433
  },
  "dropped_137": {
    "CumulativeVarianceExplained": 0.9623487073,
    "Mask": "Edge",
    "Method": "EdgeRegressor",
    "Retained": false,
    "SingularValue": 77.6959284285,
    "VarianceExplained": 0.0030254384
  },
  "dropped_138": {
    "CumulativeVarianceExplained": 0.9653534705,
    "Mask": "Edge",
    "Method": "EdgeRegressor",
    "Retained": false,
    "SingularValue": 77.4299935105,
    "VarianceExplained": 0.0030047631
  },
  "dropped_139": {
    "CumulativeVarianceExplained": 0.9683324129,
    "Mask": "Edge",
    "Method": "EdgeRegressor",
    "Retained": false,
    "SingularValue": 77.0965879578,
    "VarianceExplained": 0.0029789425
  },
  "dropped_14": {
    "CumulativeVarianceExplained": 0.4800141485,
    "Mask": "Edge",
    "Method": "EdgeRegressor",
    "Retained": false,
    "SingularValue": 101.5508290442,
    "VarianceExplained": 0.0051684313
  },
  "dropped_140": {
    "CumulativeVarianceExplained": 0.971308057,
    "Mask": "Edge",
    "Method": "EdgeRegressor",
    "Retained": false,
    "SingularValue": 77.0538935699,
    "VarianceExplained": 0.002975644
  },
  "dropped_141": {
    "CumulativeVarianceExplained": 0.9742633877,
    "Mask": "Edge",
    "Method": "EdgeRegressor",
    "Retained": false,
    "SingularValue": 76.7904379528,
    "VarianceExplained": 0.0029553307
  },
  "dropped_142": {
    "CumulativeVarianceExplained": 0.977187514,
    "Mask": "Edge",
    "Method": "EdgeRegressor",
    "Retained": false,
    "SingularValue": 76.383959307,
    "VarianceExplained": 0.0029241263
  },
  "dropped_143": {
    "CumulativeVarianceExplained": 0.980104058,
    "Mask": "Edge",
    "Method": "EdgeRegressor",
    "Retained": false,
    "SingularValue": 76.2848629492,
    "VarianceExplained": 0.002916544
  },
  "dropped_144": {
    "CumulativeVarianceExplained": 0.9830022348,
    "Mask": "Edge",
    "Method": "EdgeRegressor",
    "Retained": false,
    "SingularValue": 76.0442774857,
    "VarianceExplained": 0.0028981768
  },
  "dropped_145": {
    "CumulativeVarianceExplained": 0.9858944312,
    "Mask": "Edge",
    "Method": "EdgeRegressor",
    "Retained": false,
    "SingularValue": 75.9657784416,
    "VarianceExplained": 0.0028921964
  },
  "dropped_146": {
    "CumulativeVarianceExplained": 0.9887736595,
    "Mask": "Edge",
    "Method": "EdgeRegressor",
    "Retained": false,
    "SingularValue": 75.7952786985,
    "VarianceExplained": 0.0028792283
  },
  "dropped_147": {
    "CumulativeVarianceExplained": 0.9916373135,
    "Mask": "Edge",
    "Method": "EdgeRegressor",
    "Retained": false,
    "SingularValue": 75.5900043741,
    "VarianceExplained": 0.002863654
  },
  "dropped_148": {
    "CumulativeVarianceExplained": 0.9944679963,
    "Mask": "Edge",
    "Method": "EdgeRegressor",
    "Retained": false,
    "SingularValue": 75.153585807,
    "VarianceExplained": 0.0028306828
  },
  "dropped_149": {
    "CumulativeVarianceExplained": 0.9972507815,
    "Mask": "Edge",
    "Method": "EdgeRegressor",
    "Retained": false,
    "SingularValue": 74.5150406425,
    "VarianceExplained": 0.0027827852
  },
  "dropped_15": {
    "CumulativeVarianceExplained": 0.4851556588,
    "Mask": "Edge",
    "Method": "EdgeRegressor",
    "Retained": false,
    "SingularValue": 101.2860086679,
    "VarianceExplained": 0.0051415103
  },
  "dropped_150": {
    "CumulativeVarianceExplained": 1.0,
    "Mask": "Edge",
    "Method": "EdgeRegressor",
    "Retained": false,
    "SingularValue": 74.0642669001,
    "VarianceExplained": 0.0027492185
  },
  "dropped_151": {
    "CumulativeVarianceExplained": 1.0,
    "Mask": "Edge",
    "Method": "EdgeRegressor",
    "Retained": false,
    "SingularValue": 0.0,
    "VarianceExplained": 0.0
  },
  "dropped_152": {
    "CumulativeVarianceExplained": 1.0,
    "Mask": "Edge",
    "Method": "EdgeRegressor",
    "Retained": false,
    "SingularValue": 0.0,
    "VarianceExplained": 0.0
  },
  "dropped_153": {
    "CumulativeVarianceExplained": 1.0,
    "Mask": "Edge",
    "Method": "EdgeRegressor",
    "Retained": false,
    "SingularValue": 0.0,
    "VarianceExplained": 0.0
  },
  "dropped_154": {
    "CumulativeVarianceExplained": 1.0,
    "Mask": "Edge",
    "Method": "EdgeRegressor",
    "Retained": false,
    "SingularValue": 0.0,
    "VarianceExplained": 0.0
  },
  "dropped_155": {
    "CumulativeVarianceExplained": 1.0,
    "Mask": "Edge",
    "Method": "EdgeRegressor",
    "Retained": false,
    "SingularValue": 0.0,
    "VarianceExplained": 0.0
  },
  "dropped_16": {
    "CumulativeVarianceExplained": 0.4902790134,
    "Mask": "Edge",
    "Method": "EdgeRegressor",
    "Retained": false,
    "SingularValue": 101.1070192694,
    "VarianceExplained": 0.0051233546
  },
  "dropped_17": {
    "CumulativeVarianceExplained": 0.4953538993,
    "Mask": "Edge",
    "Method": "EdgeRegressor",
    "Retained": false,
    "SingularValue": 100.6276291744,
    "VarianceExplained": 0.0050748859
  },
  "dropped_18": {
    "CumulativeVarianceExplained": 0.500413555,
    "Mask": "Edge",
    "Method": "EdgeRegressor",
    "Retained": false,
    "SingularValue": 100.4765198458,
    "VarianceExplained": 0.0050596557
  },
  "dropped_19": {
    "CumulativeVarianceExplained": 0.5054540113,
    "Mask": "Edge",
    "Method": "EdgeRegressor",
    "Retained": false,
    "SingularValue": 100.2857048951,
    "VarianceExplained": 0.0050404564
  },
  "dropped_2": {
    "CumulativeVarianceExplained": 0.4134684936,
    "Mask": "Edge",
    "Method": "EdgeRegressor",
    "Retained": false,
    "SingularValue": 109.9409438383,
    "VarianceExplained": 0.0060577413
  },
  "dropped_20": {
    "CumulativeVarianceExplained": 0.5104421839,
    "Mask": "Edge",
    "Method": "EdgeRegressor",
    "Retained": false,
    "SingularValue": 99.7642250628,
    "VarianceExplained": 0.0049881725
  },
  "dropped_21": {
    "CumulativeVarianceExplained": 0.5153808201,
    "Mask": "Edge",
    "Method": "EdgeRegressor",
    "Retained": false,
    "SingularValue": 99.2676223663,
    "VarianceExplained": 0.0049386362
  },
  "dropped_22": {
    "CumulativeVarianceExplained": 0.5203142854,
    "Mask": "Edge",
    "Method": "EdgeRegressor",
    "Retained": false,
    "SingularValue": 99.2156404414,
    "VarianceExplained": 0.0049334653
  },
  "dropped_23": {
    "CumulativeVarianceExplained": 0.525230124,
    "Mask": "Edge",
    "Method": "EdgeRegressor",
    "Retained": false,
    "SingularValue": 99.0382390852,
    "VarianceExplained": 0.0049158386
  },
  "dropped_24": {
    "CumulativeVarianceExplained": 0.5300606975,
    "Mask": "Edge",
    "Method": "EdgeRegressor",
    "Retained": false,
    "SingularValue": 98.1755739835,
    "VarianceExplained": 0.0048305735
  },
  "dropped_25": {
    "CumulativeVarianceExplained": 0.5348439124,
    "Mask": "Edge",
    "Method": "EdgeRegressor",
    "Retained": false,
    "SingularValue": 97.6931354652,
    "VarianceExplained": 0.0047832149
  },
  "dropped_26": {
    "CumulativeVarianceExplained": 0.5396081357,
    "Mask": "Edge",
    "Method": "EdgeRegressor",
    "Retained": false,
    "SingularValue": 97.4989983682,
    "VarianceExplained": 0.0047642233
  },
  "dropped_27": {
    "CumulativeVarianceExplained": 0.5443417643,
    "Mask": "Edge",
    "Method": "EdgeRegressor",
    "Retained": false,
    "SingularValue": 97.1854369756,
    "VarianceExplained": 0.0047336286
  },
  "dropped_28": {
    "CumulativeVarianceExplained": 0.5490640182,
    "Mask": "Edge",
    "Method": "EdgeRegressor",
    "Retained": false,
    "SingularValue": 97.0686009405,
    "VarianceExplained": 0.0047222539
  },
  "dropped_29": {
    "CumulativeVarianceExplained": 0.5537498453,
    "Mask": "Edge",
    "Method": "EdgeRegressor",
    "Retained": false,
    "SingularValue": 96.6934888279,
    "VarianceExplained": 0.0046858271
  },
  "dropped_3": {
    "CumulativeVarianceExplained": 0.4194923502,
    "Mask": "Edge",
    "Method": "EdgeRegressor",
    "Retained": false,
    "SingularValue": 109.6330291894,
    "VarianceExplained": 0.0060238566
  },
  "dropped_30": {
    "CumulativeVarianceExplained": 0.5584211743,
    "Mask": "Edge",
    "Method": "EdgeRegressor",
    "Retained": false,
    "SingularValue": 96.5437863814,
    "VarianceExplained": 0.004671329
  },
  "dropped_31": {
    "CumulativeVarianceExplained": 0.5630771429,
    "Mask": "Edge",
    "Method": "EdgeRegressor",
    "Retained": false,
    "SingularValue": 96.3849266286,
    "VarianceExplained": 0.0046559686
  },
  "dropped_32": {
    "CumulativeVarianceExplained": 0.5677237534,
    "Mask": "Edge",
    "Method": "EdgeRegressor",
    "Retained": false,
    "SingularValue": 96.2880160301,
    "VarianceExplained": 0.0046466106
  },
  "dropped_33": {
    "CumulativeVarianceExplained": 0.5723260138,
    "Mask": "Edge",
    "Method": "EdgeRegressor",
    "Retained": false,
    "SingularValue": 95.8273974932,
    "VarianceExplained": 0.0046022604
  },
  "dropped_34": {
    "CumulativeVarianceExplained": 0.5769023126,
    "Mask": "Edge",
    "Method": "EdgeRegressor",
    "Retained": false,
    "SingularValue": 95.5567319231,
    "VarianceExplained": 0.0045762988
  },
  "dropped_35": {
    "CumulativeVarianceExplained": 0.5814601676,
    "Mask": "Edge",
    "Method": "EdgeRegressor",
    "Retained": false,
    "SingularValue": 95.363976743,
    "VarianceExplained": 0.004557855
  },
  "dropped_36": {
    "CumulativeVarianceExplained": 0.5859953854,
    "Mask": "Edge",
    "Method": "EdgeRegressor",
    "Retained": false,
    "SingularValue": 95.1268630895,
    "VarianceExplained": 0.0045352178
  },
  "dropped_37": {
    "CumulativeVarianceExplained": 0.5904989739,
    "Mask": "Edge",
    "Method": "EdgeRegressor",
    "Retained": false,
    "SingularValue": 94.7945686182,
    "VarianceExplained": 0.0045035886
  },
  "dropped_38": {
    "CumulativeVarianceExplained": 0.5949878882,
    "Mask": "Edge",
    "Method": "EdgeRegressor",
    "Retained": false,
    "SingularValue": 94.6400051488,
    "VarianceExplained": 0.0044889142
  },
  "dropped_39": {
    "CumulativeVarianceExplained": 0.5994723044,
    "Mask": "Edge",
    "Method": "EdgeRegressor",
    "Retained": false,
    "SingularValue": 94.5925775345,
    "VarianceExplained": 0.0044844162
  },
  "dropped_4": {
    "CumulativeVarianceExplained": 0.4253159307,
    "Mask": "Edge",
    "Method": "EdgeRegressor",
    "Retained": false,
    "SingularValue": 107.7951301135,
    "VarianceExplained": 0.0058235805
  },
  "dropped_40": {
    "CumulativeVarianceExplained": 0.6039201233,
    "Mask": "Edge",
    "Method": "EdgeRegressor",
    "Retained": false,
    "SingularValue": 94.2058014916,
    "VarianceExplained": 0.0044478189
  },
  "dropped_41": {
    "CumulativeVarianceExplained": 0.6083603366,
    "Mask": "Edge",
    "Method": "EdgeRegressor",
    "Retained": false,
    "SingularValue": 94.1252231911,
    "VarianceExplained": 0.0044402133
  },
  "dropped_42": {
    "CumulativeVarianceExplained": 0.6127702932,
    "Mask": "Edge",
    "Method": "EdgeRegressor",
    "Retained": false,
    "SingularValue": 93.8039781338,
    "VarianceExplained": 0.0044099566
  },
  "dropped_43": {
    "CumulativeVarianceExplained": 0.6171597717,
    "Mask": "Edge",
    "Method": "EdgeRegressor",
    "Retained": false,
    "SingularValue": 93.5859315036,
    "VarianceExplained": 0.0043894786
  },
  "dropped_44": {
    "CumulativeVarianceExplained": 0.621518874,
    "Mask": "Edge",
    "Method": "EdgeRegressor",
    "Retained": false,
    "SingularValue": 93.2615504455,
    "VarianceExplained": 0.0043591023
  },
  "dropped_45": {
    "CumulativeVarianceExplained": 0.6258710176,
    "Mask": "Edge",
    "Method": "EdgeRegressor",
    "Retained": false,
    "SingularValue": 93.187080892,
    "VarianceExplained": 0.0043521436
  },
  "dropped_46": {
    "CumulativeVarianceExplained": 0.6302125377,
    "Mask": "Edge",
    "Method": "EdgeRegressor",
    "Retained": false,
    "SingularValue": 93.0732784437,
    "VarianceExplained": 0.0043415202
  },
  "dropped_47": {
    "CumulativeVarianceExplained": 0.6345266248,
    "Mask": "Edge",
    "Method": "EdgeRegressor",
    "Retained": false,
    "SingularValue": 92.7787583831,
    "VarianceExplained": 0.0043140871
  },
  "dropped_48": {
    "CumulativeVarianceExplained": 0.6388343131,
    "Mask": "Edge",
    "Method": "EdgeRegressor",
    "Retained": false,
    "SingularValue": 92.7099263887,
    "VarianceExplained": 0.0043076883
  },
  "dropped_49": {
    "CumulativeVarianceExplained": 0.6431094572,
    "Mask": "Edge",
    "Method": "EdgeRegressor",
    "Retained": false,
    "SingularValue": 92.3590550809,
    "VarianceExplained": 0.0042751441
  },
  "dropped_5": {
    "CumulativeVarianceExplained": 0.4311166134,
    "Mask": "Edge",
    "Method": "EdgeRegressor",
    "Retained": false,
    "SingularValue": 107.5830017459,
    "VarianceExplained": 0.0058006827
  },
  "dropped_50": {
    "CumulativeVarianceExplained": 0.6473670392,
    "Mask": "Edge",
    "Method": "EdgeRegressor",
    "Retained": false,
    "SingularValue": 92.1691554502,
    "VarianceExplained": 0.0042575819
  },
  "dropped_51": {
    "CumulativeVarianceExplained": 0.6515911729,
    "Mask": "Edge",
    "Method": "EdgeRegressor",
    "Retained": false,
    "SingularValue": 91.8063945636,
    "VarianceExplained": 0.0042241338
  },
  "dropped_52": {
    "CumulativeVarianceExplained": 0.6558077729,
    "Mask": "Edge",
    "Method": "EdgeRegressor",
    "Retained": false,
    "SingularValue": 91.7244893333,
    "VarianceExplained": 0.0042166
  },
  "dropped_53": {
    "CumulativeVarianceExplained": 0.6599951608,
    "Mask": "Edge",
    "Method": "EdgeRegressor",
    "Retained": false,
    "SingularValue": 91.4062090524,
    "VarianceExplained": 0.0041873879
  },
  "dropped_54": {
    "CumulativeVarianceExplained": 0.6641715984,
    "Mask": "Edge",
    "Method": "EdgeRegressor",
    "Retained": false,
    "SingularValue": 91.2866138668,
    "VarianceExplained": 0.0041764376
  },
  "dropped_55": {
    "CumulativeVarianceExplained": 0.6683394091,
    "Mask": "Edge",
    "Method": "EdgeRegressor",
    "Retained": false,
    "SingularValue": 91.1922850421,
    "VarianceExplained": 0.0041678108
  },
  "dropped_56": {
    "CumulativeVarianceExplained": 0.6724849781,
    "Mask": "Edge",
    "Method": "EdgeRegressor",
    "Retained": false,
    "SingularValue": 90.9486328169,
    "VarianceExplained": 0.004145569
  },
  "dropped_57": {
    "CumulativeVarianceExplained": 0.6766255886,
    "Mask": "Edge",
    "Method": "EdgeRegressor",
    "Retained": false,
    "SingularValue": 90.8942246012,
    "VarianceExplained": 0.0041406105
  },
  "dropped_58": {
    "CumulativeVarianceExplained": 0.6807492083,
    "Mask": "Edge",
    "Method": "EdgeRegressor",
    "Retained": false,
    "SingularValue": 90.707543053,
    "VarianceExplained": 0.0041236197
  },
  "dropped_59": {
    "CumulativeVarianceExplained": 0.6848632492,
    "Mask": "Edge",
    "Method": "EdgeRegressor",
    "Retained": false,
    "SingularValue": 90.6021291858,
    "VarianceExplained": 0.0041140409
  },
  "dropped_6": {
    "CumulativeVarianceExplained": 0.4367733644,
    "Mask": "Edge",
    "Method": "EdgeRegressor",
    "Retained": false,
    "SingularValue": 106.2398948543,
    "VarianceExplained": 0.005656751
  },
  "dropped_60": {
    "CumulativeVarianceExplained": 0.6889626316,
    "Mask": "Edge",
    "Method": "EdgeRegressor",
    "Retained": false,
    "SingularValue": 90.4405755063,
    "VarianceExplained": 0.0040993824
  },
  "dropped_61": {
    "CumulativeVarianceExplained": 0.6930484143,
    "Mask": "Edge",
    "Method": "EdgeRegressor",
    "Retained": false,
    "SingularValue": 90.290432379,
    "VarianceExplained": 0.0040857827
  },
  "dropped_62": {
    "CumulativeVarianceExplained": 0.6971138898,
    "Mask": "Edge",
    "Method": "EdgeRegressor",
    "Retained": false,
    "SingularValue": 90.0657727208,
    "VarianceExplained": 0.0040654756
  },
  "dropped_63": {
    "CumulativeVarianceExplained": 0.7011742827,
    "Mask": "Edge",
    "Method": "EdgeRegressor",
    "Retained": false,
    "SingularValue": 90.0094541633,
    "VarianceExplained": 0.0040603928
  },
  "dropped_64": {
    "CumulativeVarianceExplained": 0.7052238681,
    "Mask": "Edge",
    "Method": "EdgeRegressor",
    "Retained": false,
    "SingularValue": 89.8895866506,
    "VarianceExplained": 0.0040495854
  },
  "dropped_65": {
    "CumulativeVarianceExplained": 0.7092554076,
    "Mask": "Edge",
    "Method": "EdgeRegressor",
    "Retained": false,
    "SingularValue": 89.689078553,
    "VarianceExplained": 0.0040315395
  },
  "dropped_66": {
    "CumulativeVarianceExplained": 0.7132619008,
    "Mask": "Edge",
    "Method": "EdgeRegressor",
    "Retained": false,
    "SingularValue": 89.4100426621,
    "VarianceExplained": 0.0040064931
  },
  "dropped_67": {
    "CumulativeVarianceExplained": 0.7172495004,
    "Mask": "Edge",
    "Method": "EdgeRegressor",
    "Retained": false,
    "SingularValue": 89.1989768268,
    "VarianceExplained": 0.0039875996
  },
  "dropped_68": {
    "CumulativeVarianceExplained": 0.7212204901,
    "Mask": "Edge",
    "Method": "EdgeRegressor",
    "Retained": false,
    "SingularValue": 89.0130091631,
    "VarianceExplained": 0.0039709897
  },
  "dropped_69": {
    "CumulativeVarianceExplained": 0.7251791251,
    "Mask": "Edge",
    "Method": "EdgeRegressor",
    "Retained": false,
    "SingularValue": 88.8744311381,
    "VarianceExplained": 0.003958635
  },
  "dropped_7": {
    "CumulativeVarianceExplained": 0.4423972169,
    "Mask": "Edge",
    "Method": "EdgeRegressor",
    "Retained": false,
    "SingularValue": 105.9305099466,
    "VarianceExplained": 0.0056238525
  },
  "dropped_70": {
    "CumulativeVarianceExplained": 0.7291150343,
    "Mask": "Edge",
    "Method": "EdgeRegressor",
    "Retained": false,
    "SingularValue": 88.618957385,
    "VarianceExplained": 0.0039359092
  },
  "dropped_71": {
    "CumulativeVarianceExplained": 0.7330504345,
    "Mask": "Edge",
    "Method": "EdgeRegressor",
    "Retained": false,
    "SingularValue": 88.6132265294,
    "VarianceExplained": 0.0039354001
  },
  "dropped_72": {
    "CumulativeVarianceExplained": 0.7369656512,
    "Mask": "Edge",
    "Method": "EdgeRegressor",
    "Retained": false,
    "SingularValue": 88.3856994367,
    "VarianceExplained": 0.0039152167
  },
  "dropped_73": {
    "CumulativeVarianceExplained": 0.7408652474,
    "Mask": "Edge",
    "Method": "EdgeRegressor",
    "Retained": false,
    "SingularValue": 88.2092080565,
    "VarianceExplained": 0.0038995962
  },
  "dropped_74": {
    "CumulativeVarianceExplained": 0.7447620725,
    "Mask": "Edge",
    "Method": "EdgeRegressor",
    "Retained": false,
    "SingularValue": 88.1778611751,
    "VarianceExplained": 0.0038968251
  },
  "dropped_75": {
    "CumulativeVarianceExplained": 0.748639244,
    "Mask": "Edge",
    "Method": "EdgeRegressor",
    "Retained": false,
    "SingularValue": 87.955217592,
    "VarianceExplained": 0.0038771715
  },
  "dropped_76": {
    "CumulativeVarianceExplained": 0.7525068806,
    "Mask": "Edge",
    "Method": "EdgeRegressor",
    "Retained": false,
    "SingularValue": 87.8469992511,
    "VarianceExplained": 0.0038676366
  },
  "dropped_77": {
    "CumulativeVarianceExplained": 0.7563486535,
    "Mask": "Edge",
    "Method": "EdgeRegressor",
    "Retained": false,
    "SingularValue": 87.5527803258,
    "VarianceExplained": 0.0038417728
  },
  "dropped_78": {
    "CumulativeVarianceExplained": 0.7601709816,
    "Mask": "Edge",
    "Method": "EdgeRegressor",
    "Retained": false,
    "SingularValue": 87.3309300987,
    "VarianceExplained": 0.0038223281
  },
  "dropped_79": {
    "CumulativeVarianceExplained": 0.7639889263,
    "Mask": "Edge",
    "Method": "EdgeRegressor",
    "Retained": false,
    "SingularValue": 87.2808403005,
    "VarianceExplained": 0.0038179447
  },
  "dropped_8": {
    "CumulativeVarianceExplained": 0.447944852,
    "Mask": "Edge",
    "Method": "EdgeRegressor",
    "Retained": false,
    "SingularValue": 105.2102477422,
    "VarianceExplained": 0.0055476351
  },
  "dropped_80": {
    "CumulativeVarianceExplained": 0.7678009088,
    "Mask": "Edge",
    "Method": "EdgeRegressor",
    "Retained": false,
    "SingularValue": 87.212663372,
    "VarianceExplained": 0.0038119825
  },
  "dropped_81": {
    "CumulativeVarianceExplained": 0.7716004326,
    "Mask": "Edge",
    "Method": "EdgeRegressor",
    "Retained": false,
    "SingularValue": 87.070028553,
    "VarianceExplained": 0.0037995238
  },
  "dropped_82": {
    "CumulativeVarianceExplained": 0.7753786268,
    "Mask": "Edge",
    "Method": "EdgeRegressor",
    "Retained": false,
    "SingularValue": 86.8252889432,
    "VarianceExplained": 0.0037781942
  },
  "dropped_83": {
    "CumulativeVarianceExplained": 0.7791382973,
    "Mask": "Edge",
    "Method": "EdgeRegressor",
    "Retained": false,
    "SingularValue": 86.612184585,
    "VarianceExplained": 0.0037596705
  },
  "dropped_84": {
    "CumulativeVarianceExplained": 0.7828940804,
    "Mask": "Edge",
    "Method": "EdgeRegressor",
    "Retained": false,
    "SingularValue": 86.5673961825,
    "VarianceExplained": 0.0037557831
  },
  "dropped_85": {
    "CumulativeVarianceExplained": 0.7866422499,
    "Mask": "Edge",
    "Method": "EdgeRegressor",
    "Retained": false,
    "SingularValue": 86.4796080305,
    "VarianceExplained": 0.0037481695
  },
  "dropped_86": {
    "CumulativeVarianceExplained": 0.7903771669,
    "Mask": "Edge",
    "Method": "EdgeRegressor",
    "Retained": false,
    "SingularValue": 86.3265890637,
    "VarianceExplained": 0.003734917
  },
  "dropped_87": {
    "CumulativeVarianceExplained": 0.7940991031,
    "Mask": "Edge",
    "Method": "EdgeRegressor",
    "Retained": false,
    "SingularValue": 86.1764422808,
    "VarianceExplained": 0.0037219362
  },
  "dropped_88": {
    "CumulativeVarianceExplained": 0.797795733,
    "Mask": "Edge",
    "Method": "EdgeRegressor",
    "Retained": false,
    "SingularValue": 85.8829763366,
    "VarianceExplained": 0.0036966299
  },
  "dropped_89": {
    "CumulativeVarianceExplained": 0.8014748153,
    "Mask": "Edge",
    "Method": "EdgeRegressor",
    "Retained": false,
    "SingularValue": 85.678893787,
    "VarianceExplained": 0.0036790823
  },
  "dropped_9": {
    "CumulativeVarianceExplained": 0.4534768501,
    "Mask": "Edge",
    "Method": "EdgeRegressor",
    "Retained": false,
    "SingularValue": 105.0618670466,
    "VarianceExplained": 0.0055319981
  },
  "dropped_90": {
    "CumulativeVarianceExplained": 0.8051485744,
    "Mask": "Edge",
    "Method": "EdgeRegressor",
    "Retained": false,
    "SingularValue": 85.6168882379,
    "VarianceExplained": 0.0036737591
  },
  "dropped_91": {
    "CumulativeVarianceExplained": 0.8088103571,
    "Mask": "Edge",
    "Method": "EdgeRegressor",
    "Retained": false,
    "SingularValue": 85.4772194502,
    "VarianceExplained": 0.0036617827
  },
  "dropped_92": {
    "CumulativeVarianceExplained": 0.8124518576,
    "Mask": "Edge",
    "Method": "EdgeRegressor",
    "Retained": false,
    "SingularValue": 85.2401662742,
    "VarianceExplained": 0.0036415005
  },
  "dropped_93": {
    "CumulativeVarianceExplained": 0.8160854353,
    "Mask": "Edge",
    "Method": "EdgeRegressor",
    "Retained": false,
    "SingularValue": 85.1473877187,
    "VarianceExplained": 0.0036335777
  },
  "dropped_94": {
    "CumulativeVarianceExplained": 0.8197177724,
    "Mask": "Edge",
    "Method": "EdgeRegressor",
    "Retained": false,
    "SingularValue": 85.1328500198,
    "VarianceExplained": 0.0036323371
  },
  "dropped_95": {
    "CumulativeVarianceExplained": 0.8233204209,
    "Mask": "Edge",
    "Method": "EdgeRegressor",
    "Retained": false,
    "SingularValue": 84.7842236238,
    "VarianceExplained": 0.0036026485
  },
  "dropped_96": {
    "CumulativeVarianceExplained": 0.8269198943,
    "Mask": "Edge",
    "Method": "EdgeRegressor",
    "Retained": false,
    "SingularValue": 84.7468539085,
    "VarianceExplained": 0.0035994734
  },
  "dropped_97": {
    "CumulativeVarianceExplained": 0.830508761,
    "Mask": "Edge",
    "Method": "EdgeRegressor",
    "Retained": false,
    "SingularValue": 84.6218990695,
    "VarianceExplained": 0.0035888667
  },
  "dropped_98": {
    "CumulativeVarianceExplained": 0.8340815782,
    "Mask": "Edge",
    "Method": "EdgeRegressor",
    "Retained": false,
    "SingularValue": 84.432471526,
    "VarianceExplained": 0.0035728172
  },
  "dropped_99": {
    "CumulativeVarianceExplained": 0.8376234441,
    "Mask": "Edge",
    "Method": "EdgeRegressor",
    "Retained": false,
    "SingularValue": 84.0659562348,
    "VarianceExplained": 0.0035418659
  },
  "edge_comp_00": {
    "CumulativeVarianceExplained": 0.0688490002,
    "Mask": "Edge",
    "Method": "EdgeRegressor",
    "Retained": true,
    "SingularValue": 370.6405402617,
    "VarianceExplained": 0.0688490002
  },
  "edge_comp_01": {
    "CumulativeVarianceExplained": 0.1223432161,
    "Mask": "Edge",
    "Method": "EdgeRegressor",
    "Retained": true,
    "SingularValue": 326.7063038705,
    "VarianceExplained": 0.0534942159
  },
  "edge_comp_02": {
    "CumulativeVarianceExplained": 0.1595760774,
    "Mask": "Edge",
    "Method": "EdgeRegressor",
    "Retained": true,
    "SingularValue": 272.5632553415,
    "VarianceExplained": 0.0372328613
  },
  "edge_comp_03": {
    "CumulativeVarianceExplained": 0.1849701079,
    "Mask": "Edge",
    "Method": "EdgeRegressor",
    "Retained": true,
    "SingularValue": 225.0971104818,
    "VarianceExplained": 0.0253940305
  },
  "edge_comp_04": {
    "CumulativeVarianceExplained": 0.2048419603,
    "Mask": "Edge",
    "Method": "EdgeRegressor",
    "Retained": true,
    "SingularValue": 199.1238482803,
    "VarianceExplained": 0.0198718523
  },
  "edge_comp_05": {
    "CumulativeVarianceExplained": 0.2244430724,
    "Mask": "Edge",
    "Method": "EdgeRegressor",
    "Retained": true,
    "SingularValue": 197.7627341563,
    "VarianceExplained": 0.0196011121
  },
  "edge_comp_06": {
    "CumulativeVarianceExplained": 0.241639172,
    "Mask": "Edge",
    "Method": "EdgeRegressor",
    "Retained": true,
    "SingularValue": 185.2333059,
    "VarianceExplained": 0.0171960996
  },
  "edge_comp_07": {
    "CumulativeVarianceExplained": 0.2576625012,
    "Mask": "Edge",
    "Method": "EdgeRegressor",
    "Retained": true,
    "SingularValue": 178.8053372849,
    "VarianceExplained": 0.0160233291
  },
  "edge_comp_08": {
    "CumulativeVarianceExplained": 0.271917315,
    "Mask": "Edge",
    "Method": "EdgeRegressor",
    "Retained": true,
    "SingularValue": 168.6494291934,
    "VarianceExplained": 0.0142548138
  },
  "edge_comp_09": {
    "CumulativeVarianceExplained": 0.2845365397,
    "Mask": "Edge",
    "Method": "EdgeRegressor",
    "Retained": true,
    "SingularValue": 158.6793592019,
    "VarianceExplained": 0.0126192247
  },
  "edge_comp_10": {
    "CumulativeVarianceExplained": 0.2952894056,
    "Mask": "Edge",
    "Method": "EdgeRegressor",
    "Retained": true,
    "SingularValue": 146.4759136969,
    "VarianceExplained": 0.0107528659
  },
  "edge_comp_11": {
    "CumulativeVarianceExplained": 0.3049401782,
    "Mask": "Edge",
    "Method": "EdgeRegressor",
    "Retained": true,
    "SingularValue": 138.7666627295,
    "VarianceExplained": 0.0096507727
  },
  "edge_comp_12": {
    "CumulativeVarianceExplained": 0.3139431872,
    "Mask": "Edge",
    "Method": "EdgeRegressor",
    "Retained": true,
    "SingularValue": 134.0287428862,
    "VarianceExplained": 0.009003009
  },
  "edge_comp_13": {
    "CumulativeVarianceExplained": 0.3225984818,
    "Mask": "Edge",
    "Method": "EdgeRegressor",
    "Retained": true,
    "SingularValue": 131.4150263293,
    "VarianceExplained": 0.0086552945
  },
  "edge_comp_14": {
    "CumulativeVarianceExplained": 0.3308191876,
    "Mask": "Edge",
    "Method": "EdgeRegressor",
    "Retained": true,
    "SingularValue": 128.0733159442,
    "VarianceExplained": 0.0082207058
  },
  "edge_comp_15": {
    "CumulativeVarianceExplained": 0.3386861793,
    "Mask": "Edge",
    "Method": "EdgeRegressor",
    "Retained": true,
    "SingularValue": 125.2877034072,
    "VarianceExplained": 0.0078669917
  },
  "edge_comp_16": {
    "CumulativeVarianceExplained": 0.3464447978,
    "Mask": "Edge",
    "Method": "EdgeRegressor",
    "Retained": true,
    "SingularValue": 124.4217481752,
    "VarianceExplained": 0.0077586185
  },
  "edge_comp_17": {
    "CumulativeVarianceExplained": 0.3538438308,
    "Mask": "Edge",
    "Method": "EdgeRegressor",
    "Retained": true,
    "SingularValue": 121.5042824962,
    "VarianceExplained": 0.0073990331
  },
  "edge_comp_18": {
    "CumulativeVarianceExplained": 0.361210655,
    "Mask": "Edge",
    "Method": "EdgeRegressor",
    "Retained": true,
    "SingularValue": 121.2395330955,
    "VarianceExplained": 0.0073668242
  },
  "edge_comp_19": {
    "CumulativeVarianceExplained": 0.3682282955,
    "Mask": "Edge",
    "Method": "EdgeRegressor",
    "Retained": true,
    "SingularValue": 118.3313063195,
    "VarianceExplained": 0.0070176405
  },
  "edge_comp_20": {
    "CumulativeVarianceExplained": 0.3752109792,
    "Mask": "Edge",
    "Method": "EdgeRegressor",
    "Retained": true,
    "SingularValue": 118.0362179552,
    "VarianceExplained": 0.0069826837
  },
  "edge_comp_21": {
    "CumulativeVarianceExplained": 0.3820263116,
    "Mask": "Edge",
    "Method": "EdgeRegressor",
    "Retained": true,
    "SingularValue": 116.6131754416,
    "VarianceExplained": 0.0068153324
  },
  "edge_comp_22": {
    "CumulativeVarianceExplained": 0.3886370991,
    "Mask": "Edge",
    "Method": "EdgeRegressor",
    "Retained": true,
    "SingularValue": 114.8499213274,
    "VarianceExplained": 0.0066107876
  },
  "edge_comp_23": {
    "CumulativeVarianceExplained": 0.3950316362,
    "Mask": "Edge",
    "Method": "EdgeRegressor",
    "Retained": true,
    "SingularValue": 112.9558311238,
    "VarianceExplained": 0.0063945371
  },
  "framewise_displacement": {
    "Units": "mm"
  },
  "rot_x": {
    "Description": "Rotation about left-right axis. Also known as \"pitch\".",
    "Units": "rad"
  },
  "rot_y": {
    "Description": "Rotation about anterior-posterior axis. Also known as \"roll\".",
    "Units": "rad"
  },
  "rot_z": {
    "Description": "Rotation about superior-inferior axis. Also known as \"yaw\".",
    "Units": "rad"
  },
  "t_comp_cor_00": {
    "CumulativeVarianceExplained": 0.2869817165,
    "Method": "tCompCor",
    "Retained": true,
    "SingularValue": 179.6815046308,
    "VarianceExplained": 0.2869817165
  },
  "t_comp_cor_01": {
    "CumulativeVarianceExplained": 0.5008404765,
    "Method": "tCompCor",
    "Retained": true,
    "SingularValue": 155.1099948286,
    "VarianceExplained": 0.21385876
  },
  "trans_x": {
    "Description": "Translation along left-right axis.",
    "Units": "mm"
  },
  "trans_y": {
    "Description": "Translation along anterior-posterior axis.",
    "Units": "mm"
  },
  "trans_z": {
    "Description": "Translation along superior-inferior axis.",
    "Units": "mm"
  },
  "w_comp_cor_00": {
    "CumulativeVarianceExplained": 0.0496498756,
    "Mask": "WM",
    "Method": "aCompCor",
    "Retained": true,
    "SingularValue": 100.4037387146,
    "VarianceExplained": 0.0496498756
  },
  "w_comp_cor_01": {
    "CumulativeVarianceExplained": 0.0866136213,
    "Mask": "WM",
    "Method": "aCompCor",
    "Retained": true,
    "SingularValue": 86.6320894747,
    "VarianceExplained": 0.0369637457
  },
  "w_comp_cor_02": {
    "CumulativeVarianceExplained": 0.1142296762,
    "Mask": "WM",
    "Method": "aCompCor",
    "Retained": true,
    "SingularValue": 74.8809974124,
    "VarianceExplained": 0.0276160548
  },
  "w_comp_cor_03": {
    "CumulativeVarianceExplained": 0.1351425341,
    "Mask": "WM",
    "Method": "aCompCor",
    "Retained": true,
    "SingularValue": 65.162463759,
    "VarianceExplained": 0.020912858
  },
  "w_comp_cor_04": {
    "CumulativeVarianceExplained": 0.1523456205,
    "Mask": "WM",
    "Method": "aCompCor",
    "Retained": true,
    "SingularValue": 59.1008854674,
    "VarianceExplained": 0.0172030864
  },
  "w_comp_cor_05": {
    "CumulativeVarianceExplained": 0.1683476719,
    "Mask": "WM",
    "Method": "aCompCor",
    "Retained": true,
    "SingularValue": 57.0004957239,
    "VarianceExplained": 0.0160020514
  },
  "w_comp_cor_06": {
    "CumulativeVarianceExplained": 0.1827654416,
    "Mask": "WM",
    "Method": "aCompCor",
    "Retained": true,
    "SingularValue": 54.1053042743,
    "VarianceExplained": 0.0144177697
  },
  "w_comp_cor_07": {
    "CumulativeVarianceExplained": 0.1953422602,
    "Mask": "WM",
    "Method": "aCompCor",
    "Retained": true,
    "SingularValue": 50.5331302625,
    "VarianceExplained": 0.0125768186
  },
  "w_comp_cor_08": {
    "CumulativeVarianceExplained": 0.2067009314,
    "Mask": "WM",
    "Method": "aCompCor",
    "Retained": true,
    "SingularValue": 48.0235837371,
    "VarianceExplained": 0.0113586712
  },
  "w_comp_cor_09": {
    "CumulativeVarianceExplained": 0.2177113714,
    "Mask": "WM",
    "Method": "aCompCor",
    "Retained": true,
    "SingularValue": 47.2817062644,
    "VarianceExplained": 0.01101044
  },
  "w_comp_cor_10": {
    "CumulativeVarianceExplained": 0.2282804359,
    "Mask": "WM",
    "Method": "aCompCor",
    "Retained": true,
    "SingularValue": 46.3243223789,
    "VarianceExplained": 0.0105690644
  },
  "w_comp_cor_11": {
    "CumulativeVarianceExplained": 0.2385611767,
    "Mask": "WM",
    "Method": "aCompCor",
    "Retained": true,
    "SingularValue": 45.6880904637,
    "VarianceExplained": 0.0102807408
  },
  "w_comp_cor_12": {
    "CumulativeVarianceExplained": 0.2481192302,
    "Mask": "WM",
    "Method": "aCompCor",
    "Retained": true,
    "SingularValue": 44.0530042592,
    "VarianceExplained": 0.0095580535
  },
  "w_comp_cor_13": {
    "CumulativeVarianceExplained": 0.2575675874,
    "Mask": "WM",
    "Method": "aCompCor",
    "Retained": true,
    "SingularValue": 43.7994800089,
    "VarianceExplained": 0.0094483572
  },
  "w_comp_cor_14": {
    "CumulativeVarianceExplained": 0.2668761372,
    "Mask": "WM",
    "Method": "aCompCor",
    "Retained": true,
    "SingularValue": 43.4742218388,
    "VarianceExplained": 0.0093085499
  },
  "w_comp_cor_15": {
    "CumulativeVarianceExplained": 0.2760419111,
    "Mask": "WM",
    "Method": "aCompCor",
    "Retained": true,
    "SingularValue": 43.1395262734,
    "VarianceExplained": 0.0091657739
  },
  "w_comp_cor_16": {
    "CumulativeVarianceExplained": 0.2849848172,
    "Mask": "WM",
    "Method": "aCompCor",
    "Retained": true,
    "SingularValue": 42.6118252986,
    "VarianceExplained": 0.0089429061
  },
  "w_comp_cor_17": {
    "CumulativeVarianceExplained": 0.2938576676,
    "Mask": "WM",
    "Method": "aCompCor",
    "Retained": true,
    "SingularValue": 42.4445938845,
    "VarianceExplained": 0.0088728504
  },
  "w_comp_cor_18": {
    "CumulativeVarianceExplained": 0.3026129956,
    "Mask": "WM",
    "Method": "aCompCor",
    "Retained": true,
    "SingularValue": 42.1625637089,
    "VarianceExplained": 0.0087553279
  },
  "w_comp_cor_19": {
    "CumulativeVarianceExplained": 0.3112745465,
    "Mask": "WM",
    "Method": "aCompCor",
    "Retained": true,
    "SingularValue": 41.9361574059,
    "VarianceExplained": 0.0086615509
  },
  "w_comp_cor_20": {
    "CumulativeVarianceExplained": 0.3198144699,
    "Mask": "WM",
    "Method": "aCompCor",
    "Retained": true,
    "SingularValue": 41.6406779696,
    "VarianceExplained": 0.0085399235
  },
  "w_comp_cor_21": {
    "CumulativeVarianceExplained": 0.3282412676,
    "Mask": "WM",
    "Method": "aCompCor",
    "Retained": true,
    "SingularValue": 41.3639578128,
    "VarianceExplained": 0.0084267977
  },
  "w_comp_cor_22": {
    "CumulativeVarianceExplained": 0.3365603159,
    "Mask": "WM",
    "Method": "aCompCor",
    "Retained": true,
    "SingularValue": 41.0986563263,
    "VarianceExplained": 0.0083190482
  },
  "w_comp_cor_23": {
    "CumulativeVarianceExplained": 0.3447673485,
    "Mask": "WM",
    "Method": "aCompCor",
    "Retained": true,
    "SingularValue": 40.8210228277,
    "VarianceExplained": 0.0082070326
  },
  "w_comp_cor_24": {
    "CumulativeVarianceExplained": 0.3528807055,
    "Mask": "WM",
    "Method": "aCompCor",
    "Retained": true,
    "SingularValue": 40.5873872005,
    "VarianceExplained": 0.008113357
  },
  "w_comp_cor_25": {
    "CumulativeVarianceExplained": 0.360931373,
    "Mask": "WM",
    "Method": "aCompCor",
    "Retained": true,
    "SingularValue": 40.4302798393,
    "VarianceExplained": 0.0080506675
  },
  "w_comp_cor_26": {
    "CumulativeVarianceExplained": 0.3688457717,
    "Mask": "WM",
    "Method": "aCompCor",
    "Retained": true,
    "SingularValue": 40.0866501018,
    "VarianceExplained": 0.0079143987
  },
  "w_comp_cor_27": {
    "CumulativeVarianceExplained": 0.3767080225,
    "Mask": "WM",
    "Method": "aCompCor",
    "Retained": true,
    "SingularValue": 39.9543666287,
    "VarianceExplained": 0.0078622509
  },
  "w_comp_cor_28": {
    "CumulativeVarianceExplained": 0.3845000726,
    "Mask": "WM",
    "Method": "aCompCor",
    "Retained": true,
    "SingularValue": 39.7755935504,
    "VarianceExplained": 0.0077920501
  },
  "w_comp_cor_29": {
    "CumulativeVarianceExplained": 0.3921336338,
    "Mask": "WM",
    "Method": "aCompCor",
    "Retained": true,
    "SingularValue": 39.3690012634,
    "VarianceExplained": 0.0076335612
  },
  "w_comp_cor_30": {
    "CumulativeVarianceExplained": 0.3996996068,
    "Mask": "WM",
    "Method": "aCompCor",
    "Retained": true,
    "SingularValue": 39.1943257655,
    "VarianceExplained": 0.0075659731
  },
  "w_comp_cor_31": {
    "CumulativeVarianceExplained": 0.4071363188,
    "Mask": "WM",
    "Method": "aCompCor",
    "Retained": true,
    "SingularValue": 38.8580751322,
    "VarianceExplained": 0.007436712
  },
  "w_comp_cor_32": {
    "CumulativeVarianceExplained": 0.4145503644,
    "Mask": "WM",
    "Method": "aCompCor",
    "Retained": true,
    "SingularValue": 38.7988120081,
    "VarianceExplained": 0.0074140456
  },
  "w_comp_cor_33": {
    "CumulativeVarianceExplained": 0.4219523799,
    "Mask": "WM",
    "Method": "aCompCor",
    "Retained": true,
    "SingularValue": 38.7673215613,
    "VarianceExplained": 0.0074020155
  },
  "w_comp_cor_34": {
    "CumulativeVarianceExplained": 0.4292149182,
    "Mask": "WM",
    "Method": "aCompCor",
    "Retained": true,
    "SingularValue": 38.4003357086,
    "VarianceExplained": 0.0072625383
  },
  "w_comp_cor_35": {
    "CumulativeVarianceExplained": 0.4364356061,
    "Mask": "WM",
    "Method": "aCompCor",
    "Retained": true,
    "SingularValue": 38.2895347398,
    "VarianceExplained": 0.0072206879
  },
  "w_comp_cor_36": {
    "CumulativeVarianceExplained": 0.4435664767,
    "Mask": "WM",
    "Method": "aCompCor",
    "Retained": true,
    "SingularValue": 38.050649939,
    "VarianceExplained": 0.0071308706
  },
  "w_comp_cor_37": {
    "CumulativeVarianceExplained": 0.4505887017,
    "Mask": "WM",
    "Method": "aCompCor",
    "Retained": true,
    "SingularValue": 37.7596685627,
    "VarianceExplained": 0.007022225
  },
  "w_comp_cor_38": {
    "CumulativeVarianceExplained": 0.4576046409,
    "Mask": "WM",
    "Method": "aCompCor",
    "Retained": true,
    "SingularValue": 37.7427648586,
    "VarianceExplained": 0.0070159392
  },
  "w_comp_cor_39": {
    "CumulativeVarianceExplained": 0.4645659984,
    "Mask": "WM",
    "Method": "aCompCor",
    "Retained": true,
    "SingularValue": 37.5956648746,
    "VarianceExplained": 0.0069613575
  },
  "w_comp_cor_40": {
    "CumulativeVarianceExplained": 0.4714207781,
    "Mask": "WM",
    "Method": "aCompCor",
    "Retained": true,
    "SingularValue": 37.3067618753,
    "VarianceExplained": 0.0068547798
  },
  "w_comp_cor_41": {
    "CumulativeVarianceExplained": 0.4781090436,
    "Mask": "WM",
    "Method": "aCompCor",
    "Retained": true,
    "SingularValue": 36.8508536575,
    "VarianceExplained": 0.0066882654
  },
  "w_comp_cor_42": {
    "CumulativeVarianceExplained": 0.4847715976,
    "Mask": "WM",
    "Method": "aCompCor",
    "Retained": true,
    "SingularValue": 36.779953273,
    "VarianceExplained": 0.006662554
  },
  "w_comp_cor_43": {
    "CumulativeVarianceExplained": 0.4913992337,
    "Mask": "WM",
    "Method": "aCompCor",
    "Retained": true,
    "SingularValue": 36.6834465595,
    "VarianceExplained": 0.0066276362
  },
  "w_comp_cor_44": {
    "CumulativeVarianceExplained": 0.4979527742,
    "Mask": "WM",
    "Method": "aCompCor",
    "Retained": true,
    "SingularValue": 36.477813279,
    "VarianceExplained": 0.0065535405
  },
  "w_comp_cor_45": {
    "CumulativeVarianceExplained": 0.5044871052,
    "Mask": "WM",
    "Method": "aCompCor",
    "Retained": true,
    "SingularValue": 36.4243127362,
    "VarianceExplained": 0.006534331
  }
}